setup.py
pydependschecker/Checker.py
pydependschecker/Errors.py
pydependschecker/__init__.py
pydependschecker.egg-info/PKG-INFO
pydependschecker.egg-info/SOURCES.txt
pydependschecker.egg-info/dependency_links.txt
pydependschecker.egg-info/top_level.txt
test/__init__.py
test/test.py