Metadata-Version: 1.1
Name: pydependschecker
Version: 0.1
Summary: A pure-python dependency graph generator and checker
Home-page: https://github.com/sys-git/pydependschecker
Author: Francis Horsman
Author-email: francis.horsman@gmail.com
License: GNU General Public License
Platform: UNKNOWN
Classifier: Development Status :: 4 - Beta
Classifier: Intended Audience :: Developers
Classifier: License :: OSI Approved :: BSD License
Classifier: Operating System :: OS Independent
Classifier: Programming Language :: Python
Classifier: Topic :: Communications
